{
  "chunk_id": "chunk_004",
  "category": "stories-honoring-a-decade-of-dedication-at-dialysis-care-center",
  "file_path": "c:\\Users\\default.LAPTOP-3RO2LG6Q\\Documents\\GitHub\\QA_Chat\\data\\chunks\\stories-honoring-a-decade-of-dedication-at-dialysis-care-center\\chunk_004.txt",
  "content": "Her proudest moments come when patients personally acknowledge her care. She values DCC’s open communication and collaboration. She finds it refreshing that everyone enjoys talking to each other here. Her advice to newcomers: If you’re passionate about dialysis and patient care, DCC is the right place for you. Cristina G. Senior Manager, Revenue Cycle Management Fresh out of medical billing school, Cristina joined KCC with no experience, grateful for the opportunity to learn. She started as a Biller and transitioned into DCC’s early days, working in a small but mighty three-woman team. Over the years, she earned her current title, proving that hard work never goes unnoticed. She values her department and the flexibility to work from a clinic closer to home. Her advice? “Give it your all – your efforts will be recognized.” Amanda M. Director, Home HHD/TCU/ETD Amanda took a chance on peritoneal dialysis and quickly realized it was her calling. The deep connections she formed with patients and their families made this role the most rewarding in her career. She takes pride in being part of DCC’s growth and success. Her advice to others: Stay committed to patient care – DCC recognizes and values hard work.",
  "url": "https://dccdialysis.com/stories/honoring-a-decade-of-dedication-at-dialysis-care-center/",
  "title": "Honoring a Decade of Dedication at Dialysis Care Center"
}